[{"senderKeyId":1500032299,"senderChainKey":{"iteration":187,"seed":"gTIiSGth38QhFFjU6S+sap5KenI8THFk305CNwp52+c="},"senderSigningKey":{"public":"BSCxiBD+qMl9qwwE517rrGI/9rSn7KK1gKRbojO/I2FJ","private":"6C7khiiH5M166iuPs0zB1bml8mea2RdHkN/Gd+YyM0k="},"senderMessageKeys":[{},{},{},{},{},{},{},{},{},{},{},{},{},{},{},{},{},{},{},{},{},{},{},{},{},{},{},{},{},{},{},{},{},{},{},{},{},{},{},{},{},{},{},{},{},{},{},{},{},{},{},{},{},{},{},{},{},{},{},{},{},{},{},{},{},{},{},{},{},{},{},{},{},{},{},{},{},{},{},{},{},{},{},{},{},{},{},{},{},{},{},{},{}]}]