[{"senderKeyId":1966089291,"senderChainKey":{"iteration":155,"seed":"fwyAuRXonWTALwwVoHZQeLCydrMZN5fLJqGZVL/eFIU="},"senderSigningKey":{"public":"BaToNdh7cM2WTnDb0Rz5MgbctaRXwp0WQZYIn9RtC65E","private":"+DWJI9Dofdd5C8G3UdUU9pPclV8q4ex2zKjWoka/bGY="},"senderMessageKeys":[{},{},{},{},{},{},{},{},{},{},{},{},{},{},{},{},{},{},{},{},{},{},{},{},{},{},{},{},{},{},{},{},{},{},{},{},{},{},{},{},{},{},{},{},{},{},{},{},{},{},{},{},{},{},{},{},{},{},{},{},{},{},{},{},{},{},{},{},{},{},{},{},{},{},{},{},{}]}]